blair_wdq/__init__.py
blair_wdq/client.py
blair_wdq/environment.py
blair_wdq/core/__init__.py
blair_wdq/core/api_error.py
blair_wdq/core/client_wrapper.py
blair_wdq/core/datetime_utils.py
blair_wdq/core/file.py
blair_wdq/core/http_client.py
blair_wdq/core/jsonable_encoder.py
blair_wdq/core/pydantic_utilities.py
blair_wdq/core/query_encoder.py
blair_wdq/core/remove_none_from_dict.py
blair_wdq/core/request_options.py
blair_wdq/types/__init__.py
blair_wdq/types/post_speech_demucs_response.py
blair_wdq/types/post_speech_enhance_response.py
blair_wdq/types/post_speech_inference_response.py
blair_wdq/types/post_speech_inpaint_response.py
blair_wdq/types/post_speech_transcribe_response.py
core/__init__.py
core/api_error.py
core/client_wrapper.py
core/datetime_utils.py
core/file.py
core/http_client.py
core/jsonable_encoder.py
core/pydantic_utilities.py
core/query_encoder.py
core/remove_none_from_dict.py
core/request_options.py
types/__init__.py
types/post_speech_demucs_response.py
types/post_speech_enhance_response.py
types/post_speech_inference_response.py
types/post_speech_inpaint_response.py
types/post_speech_transcribe_response.py
blair_wdq-0.1.2.dist-info/METADATA
blair_wdq-0.1.2.dist-info/WHEEL
blair_wdq-0.1.2.dist-info/top_level.txt
blair_wdq-0.1.2.dist-info/RECORD
