Metadata-Version: 2.1
Name: blair-wdq
Version: 0.1.2
Summary: Python SDK for Deeptune Text-to-Speech API
Home-page: https://github.com/yourusername/blair-wdq
Author: Your Name
Author-email: your.email@example.com
Classifier: Development Status :: 3 - Alpha
Classifier: Intended Audience :: Developers
Classifier: License :: OSI Approved :: MIT License
Classifier: Programming Language :: Python :: 3.7
Classifier: Programming Language :: Python :: 3.8
Classifier: Programming Language :: Python :: 3.9
Classifier: Programming Language :: Python :: 3.10
Requires-Python: >=3.7
Requires-Dist: requests
